<?xml version="1.0" encoding="utf-8"?>
<version>
	<awardking>
		<ver code="1.2.0" index="1">true</ver>
	</awardking>
	<android>
		<ver code="1.0.0" index="1" url="http://cpapk.6636.com:82/shouji/download/yuncai_default_v1011_ser.apk" instruction="本次更新内容...">false</ver>
		<ver code="1.0.1" index="2" url="http://cpapk.6636.com:82/shouji/download/yuncai_default_v1012_ser.apk" instruction="本次更新内容...">false</ver>
		<ver code="1.0.2" index="3" url="http://cpapk.6636.com:82/shouji/download/yuncai_v1.0.3_ser.apk" instruction="本次更新内容...">true</ver>
		<ver code="1.0.3" index="4" url="http://cpapk.6636.com:82/shouji/download/yuncai_v1.0.4_ser.apk" instruction="本次更新内容...">true</ver>
		<ver code="1.0.4" index="5" url="http://cpapk.6636.com:82/shouji/download/yuncai_v1.0.5_ser.apk" instruction="本次更新内容...">true</ver>
	</android>
	<iphone>
		<ver code="1.2.0" index="1">true</ver>
	</iphone>
	<ipad>
		<ver code="1.2.0" index="1">true</ver>
	</ipad>
</version>