<?xml version="1.0" encoding="utf-8"?>
<!DOCTYPE hibernate-mapping PUBLIC "-//Hibernate/Hibernate Mapping DTD 3.0//EN"
"http://hibernate.sourceforge.net/hibernate-mapping-3.0.dtd">
<!-- 
    Mapping file autogenerated by MyEclipse Persistence Tools
-->
<hibernate-mapping>
    <class name="com.yuncai.modules.lottery.model.Oracle.FollowingPlanInfo" table="t_following_plan_info">
        <id name="planNo" type="java.lang.Integer">
            <column name="plan_no" />
            <generator class="assigned" />
        </id>
        <property name="followingType" type="java.lang.Integer">
            <column name="following_type" />
        </property>
        <property name="planStatus" type="java.lang.Integer">
            <column name="plan_status" />
        </property>
        <property name="processedStatus" type="java.lang.Integer">
            <column name="processed_status" />
        </property>
    </class>
</hibernate-mapping>
