<?xml version="1.0" encoding="utf-8"?>
<!DOCTYPE hibernate-mapping PUBLIC "-//Hibernate/Hibernate Mapping DTD 3.0//EN"
"http://hibernate.sourceforge.net/hibernate-mapping-3.0.dtd">
<!-- 
    Mapping file autogenerated by MyEclipse Persistence Tools
-->
<hibernate-mapping>
    <class name="com.yuncai.modules.lottery.model.Oracle.Ticket" table="t_ticket">
        <id name="id" type="java.lang.Integer">
            <column name="id" />
          		<generator class="sequence">  
    				<param name="sequence">s_ticket</param>  
    			</generator>
        </id>
        <property name="planNo" type="java.lang.Integer">
            <column name="PLAN_NO" not-null="true" />
        </property>
        <property name="content" type="java.lang.String">
            <column name="CONTENT" length="65535" />
        </property>
        <property name="term" type="java.lang.String">
            <column name="TERM" length="20" not-null="true" />
        </property>
        <property name="lotteryType" >
            <column name="LOTTERY_TYPE" not-null="true" />
            <type name="com.yuncai.core.hibernate.IntegerBeanLabelUserType">
				<param name="targetClass">
					com.yuncai.modules.lottery.model.Oracle.toolType.LotteryType
				</param>
			</type>
        </property>
        <property name="amount" type="java.lang.Integer">
            <column name="AMOUNT" />
        </property>
        <property name="createDateTime" type="java.util.Date">
            <column name="CREATE_DATE_TIME" length="19" not-null="true" />
        </property>
        <property name="sendDateTime" type="java.util.Date">
            <column name="SEND_DATE_TIME" length="19" />
        </property>
        <property name="printDateTime" type="java.util.Date">
            <column name="PRINT_DATE_TIME" length="19" />
        </property>
        <property name="dealDateTime" type="java.util.Date">
            <column name="DEAL_DATE_TIME" length="19" not-null="true" />
        </property>
        <property name="multiple" type="java.lang.Integer">
            <column name="MULTIPLE" not-null="true" />
        </property>
        <property name="playType" >
            <column name="PLAY_TYPE" not-null="true" />
            <type name="com.yuncai.core.hibernate.IntegerBeanLabelUserType">
				<param name="targetClass">
					com.yuncai.modules.lottery.model.Oracle.toolType.PlayType
				</param>
			</type>
        </property>
        <property name="isBingo" type="java.lang.Integer">
            <column name="IS_BINGO" />
        </property>
        <property name="bingoAmount" type="java.lang.Double">
            <column name="BINGO_AMOUNT" />
        </property>
        <property name="bingoContent" type="java.lang.String">
            <column name="BINGO_CONTENT" length="65535" />
        </property>
        <property name="status" >
            <column name="STATUS" not-null="true" />
            <type name="com.yuncai.core.hibernate.IntegerBeanLabelUserType">
				<param name="targetClass">
					com.yuncai.modules.lottery.model.Oracle.toolType.TicketStatus
				</param>
			</type>
        </property>
        <property name="addAttribute" type="java.lang.String">
            <column name="ADD_ATTRIBUTE" length="200" />
        </property>
        <property name="account" type="java.lang.String">
            <column name="ACCOUNT" length="50" not-null="true" />
        </property>
        <property name="outId" type="java.lang.String">
            <column name="OUT_ID" length="30" />
        </property>
        <property name="noInBatch" type="java.lang.Integer">
            <column name="NO_IN_BATCH" />
        </property>
        <property name="batchNo" type="java.lang.String">
            <column name="BATCH_NO" length="20" />
        </property>
        <property name="isConvert" type="java.lang.Integer">
            <column name="IS_CONVERT" />
        </property>
        <property name="convertDateTime" type="java.util.Date">
            <column name="CONVERT_DATE_TIME" length="19" />
        </property>
        <property name="serialNo" type="java.lang.String">
            <column name="SERIAL_NO" length="50" />
        </property>
        <property name="provider" >
            <column name="PROVIDER" not-null="true" />
            <type name="com.yuncai.core.hibernate.IntegerBeanLabelUserType">
				<param name="targetClass">
					com.yuncai.modules.lottery.model.Oracle.toolType.TicketProvider
				</param>
			</type>
        </property>
        <property name="SP" type="java.lang.String">
            <column name="SP" length="65535" />
        </property>
        <property name="boZhongContent" type="java.lang.String">
            <column name="BOZHONGCONTENT" length="65535" />
        </property>
    </class>
</hibernate-mapping>
